Report_2/alu_8bit.v
// ============================================================
// 8-bit Arithmetic Logic Unit (ALU)
// ============================================================

module alu_8bit (
    input  [7:0] A,        // First 8-bit input operand
    input  [7:0] B,        // Second 8-bit input operand
    input  [2:0] sel,      // Operation select input

    output reg [7:0] result, // 8-bit ALU output
    output reg       carry,  // Carry / borrow / shifted-out bit
    output reg       zero    // Zero flag
);

    // Combinational ALU logic
    always @(*) begin

        // Default values prevent latch generation
        result = 8'b00000000;
        carry  = 1'b0;
        zero   = 1'b0;

        // Select ALU operation
        case (sel)

            // ------------------------------------------------
            // 000: Addition
            // result = A + B
            // carry stores the 9th bit of the addition result
            // ------------------------------------------------
            3'b000: begin
                {carry, result} = A + B;
            end

            // ------------------------------------------------
            // 001: Subtraction
            // result = A - B
            // carry = 1 means borrow occurred, i.e., A < B
            // ------------------------------------------------
            3'b001: begin
                result = A - B;

                if (A < B)
                    carry = 1'b1;   // Borrow occurred
                else
                    carry = 1'b0;   // No borrow
            end

            // ------------------------------------------------
            // 010: Bitwise AND
            // ------------------------------------------------
            3'b010: begin
                result = A & B;
            end

            // ------------------------------------------------
            // 011: Bitwise OR
            // ------------------------------------------------
            3'b011: begin
                result = A | B;
            end

            // ------------------------------------------------
            // 100: Bitwise XOR
            // ------------------------------------------------
            3'b100: begin
                result = A ^ B;
            end

            // ------------------------------------------------
            // 101: Bitwise NOT of A
            // B is not used in this operation
            // ------------------------------------------------
            3'b101: begin
                result = ~A;
            end

            // ------------------------------------------------
            // 110: Logical left shift of A by one bit
            // A[7] is shifted out and stored in carry
            // ------------------------------------------------
            3'b110: begin
                result = A << 1;
                carry  = A[7];
            end

            // ------------------------------------------------
            // 111: Logical right shift of A by one bit
            // A[0] is shifted out and stored in carry
            // ------------------------------------------------
            3'b111: begin
                result = A >> 1;
                carry  = A[0];
            end

            // Default case for safety
            default: begin
                result = 8'b00000000;
                carry  = 1'b0;
            end

        endcase

        // ----------------------------------------------------
        // Zero flag generation
        // zero = 1 when result is exactly 00000000
        // ----------------------------------------------------
        if (result == 8'b00000000)
            zero = 1'b1;
        else
            zero = 1'b0;

    end

endmodule

Report_2/alu_8bit_tb.v
// ============================================================
// Description: Testbench for 8-bit ALU
// ============================================================

`timescale 1ns/1ps

module alu_8bit_tb;

    // Testbench input signals
    reg [7:0] A;
    reg [7:0] B;
    reg [2:0] sel;

    // Testbench output signals
    wire [7:0] result;
    wire       carry;
    wire       zero;

    // --------------------------------------------------------
    // Instantiate the ALU module
    // --------------------------------------------------------
    alu_8bit uut (
        .A(A),
        .B(B),
        .sel(sel),
        .result(result),
        .carry(carry),
        .zero(zero)
    );

    // --------------------------------------------------------
    // Task for automatically checking expected output
    // --------------------------------------------------------
    task check_output;
        input [7:0] expected_result;
        input       expected_carry;
        input       expected_zero;

        begin
            if ((result === expected_result) &&
                (carry  === expected_carry) &&
                (zero   === expected_zero)) begin

                $display("PASS --> Result=%h Carry=%b Zero=%b",
                         result, carry, zero);
            end

            else begin
                $display("FAIL --> Got: Result=%h Carry=%b Zero=%b",
                         result, carry, zero);

                $display("          Expected: Result=%h Carry=%b Zero=%b",
                         expected_result, expected_carry, expected_zero);
            end
        end
    endtask

    // --------------------------------------------------------
    // Apply different test cases
    // --------------------------------------------------------
    initial begin

        // Generate waveform file for GTKWave
        $dumpfile("alu_8bit.vcd");
        $dumpvars(0, alu_8bit_tb);

        // Print a heading in terminal
        $display("==============================================");
        $display("       8-BIT ALU VERILOG SIMULATION");
        $display("==============================================");

        // Initialize all inputs
        A   = 8'b00000000;
        B   = 8'b00000000;
        sel = 3'b000;

        #10;

        // ----------------------------------------------------
        // Test 1: Addition
        // 05 + 03 = 08
        // ----------------------------------------------------
        $display("\nTest 1: Addition");
        A   = 8'h05;
        B   = 8'h03;
        sel = 3'b000;

        #10;
        check_output(8'h08, 1'b0, 1'b0);

        // ----------------------------------------------------
        // Test 2: Addition with carry
        // FF + 01 = 100 hexadecimal
        // Result = 00 and Carry = 1
        // ----------------------------------------------------
        $display("\nTest 2: Addition with Carry");
        A   = 8'hFF;
        B   = 8'h01;
        sel = 3'b000;

        #10;
        check_output(8'h00, 1'b1, 1'b1);

        // ----------------------------------------------------
        // Test 3: Subtraction without borrow
        // 0A - 04 = 06
        // ----------------------------------------------------
        $display("\nTest 3: Subtraction without Borrow");
        A   = 8'h0A;
        B   = 8'h04;
        sel = 3'b001;

        #10;
        check_output(8'h06, 1'b0, 1'b0);

        // ----------------------------------------------------
        // Test 4: Subtraction with borrow
        // 03 - 05 = FE in 8-bit two's complement
        // Borrow = 1
        // ----------------------------------------------------
        $display("\nTest 4: Subtraction with Borrow");
        A   = 8'h03;
        B   = 8'h05;
        sel = 3'b001;

        #10;
        check_output(8'hFE, 1'b1, 1'b0);

        // ----------------------------------------------------
        // Test 5: AND operation
        // AA AND 0F = 0A
        // ----------------------------------------------------
        $display("\nTest 5: AND Operation");
        A   = 8'hAA;
        B   = 8'h0F;
        sel = 3'b010;

        #10;
        check_output(8'h0A, 1'b0, 1'b0);

        // ----------------------------------------------------
        // Test 6: OR operation
        // A0 OR 0F = AF
        // ----------------------------------------------------
        $display("\nTest 6: OR Operation");
        A   = 8'hA0;
        B   = 8'h0F;
        sel = 3'b011;

        #10;
        check_output(8'hAF, 1'b0, 1'b0);

        // ----------------------------------------------------
        // Test 7: XOR operation
        // AA XOR 0F = A5
        // ----------------------------------------------------
        $display("\nTest 7: XOR Operation");
        A   = 8'hAA;
        B   = 8'h0F;
        sel = 3'b100;

        #10;
        check_output(8'hA5, 1'b0, 1'b0);

        // ----------------------------------------------------
        // Test 8: NOT operation
        // NOT 0F = F0
        // ----------------------------------------------------
        $display("\nTest 8: NOT Operation");
        A   = 8'h0F;
        B   = 8'h00;
        sel = 3'b101;

        #10;
        check_output(8'hF0, 1'b0, 1'b0);

        // ----------------------------------------------------
        // Test 9: Left shift
        // 91 = 10010001
        // 91 << 1 = 22
        // Carry = original MSB = 1
        // ----------------------------------------------------
        $display("\nTest 9: Left Shift");
        A   = 8'h91;
        B   = 8'h00;
        sel = 3'b110;

        #10;
        check_output(8'h22, 1'b1, 1'b0);

        // ----------------------------------------------------
        // Test 10: Right shift
        // 91 = 10010001
        // 91 >> 1 = 48
        // Carry = original LSB = 1
        // ----------------------------------------------------
        $display("\nTest 10: Right Shift");
        A   = 8'h91;
        B   = 8'h00;
        sel = 3'b111;

        #10;
        check_output(8'h48, 1'b1, 1'b0);

        // ----------------------------------------------------
        // Test 11: Zero flag test
        // 45 - 45 = 00
        // zero flag must become 1
        // ----------------------------------------------------
        $display("\nTest 11: Zero Flag Test");
        A   = 8'h45;
        B   = 8'h45;
        sel = 3'b001;

        #10;
        check_output(8'h00, 1'b0, 1'b1);

        // End simulation
        $display("\n==============================================");
        $display("Simulation completed.");
        $display("==============================================");

        #10;
        $finish;
    end

endmodule

Report_2/alu_8bit.vcd
$date
	Tue Jul 07 14:40:35 2026
$end
$version
	Icarus Verilog
$end
$timescale
	1ps
$end
$scope module alu_8bit_tb $end
$var wire 1 ! zero $end
$var wire 8 " result [7:0] $end
$var wire 1 # carry $end
$var reg 8 $ A [7:0] $end
$var reg 8 % B [7:0] $end
$var reg 3 & sel [2:0] $end
$scope module uut $end
$var wire 8 ' A [7:0] $end
$var wire 8 ( B [7:0] $end
$var wire 3 ) sel [2:0] $end
$var reg 1 # carry $end
$var reg 8 * result [7:0] $end
$var reg 1 ! zero $end
$upscope $end
$scope task check_output $end
$var reg 1 + expected_carry $end
$var reg 8 , expected_result [7:0] $end
$var reg 1 - expected_zero $end
$upscope $end
$upscope $end
$enddefinitions $end
$comment Show the parameter values. $end
$dumpall
$end
#0
$dumpvars
x-
bx ,
x+
b0 *
b0 )
b0 (
b0 '
b0 &
b0 %
b0 $
0#
b0 "
1!
$end
#10000
b1000 "
b1000 *
0!
b11 %
b11 (
b101 $
b101 '
#20000
1!
1#
b0 "
b0 *
b1 %
b1 (
b11111111 $
b11111111 '
0-
0+
b1000 ,
#30000
b110 "
b110 *
0!
0#
b1 &
b1 )
b100 %
b100 (
b1010 $
b1010 '
1-
1+
b0 ,
#40000
1#
b11111110 "
b11111110 *
b101 %
b101 (
b11 $
b11 '
0-
0+
b110 ,
#50000
0#
b1010 "
b1010 *
b10 &
b10 )
b1111 %
b1111 (
b10101010 $
b10101010 '
1+
b11111110 ,
#60000
b10101111 "
b10101111 *
b11 &
b11 )
b10100000 $
b10100000 '
0+
b1010 ,
#70000
b10100101 "
b10100101 *
b100 &
b100 )
b10101010 $
b10101010 '
b10101111 ,
#80000
b11110000 "
b11110000 *
b101 &
b101 )
b0 %
b0 (
b1111 $
b1111 '
b10100101 ,
#90000
1#
b100010 "
b100010 *
b110 &
b110 )
b10010001 $
b10010001 '
b11110000 ,
#100000
1#
b1001000 "
b1001000 *
b111 &
b111 )
1+
b100010 ,
#110000
1!
0#
b0 "
b0 *
b1 &
b1 )
b1000101 %
b1000101 (
b1000101 $
b1000101 '
b1001000 ,
#120000
1-
0+
b0 ,
