Report_1/n_to_1_mux.v

module n_to_1_mux #(
    parameter N = 32,             // Number of inputs
    parameter WIDTH = 8,         // Width of each input
    parameter SEL_WIDTH = 5      // log2(N), for N=32 --> 5 bits
)(
    input  [N*WIDTH-1:0] data_in,  // Combined input bus
    input  [SEL_WIDTH-1:0] sel,    // Select line
    output reg [WIDTH-1:0] d_out   // Selected output
);

    always @(*) begin
       
    // Check whether the selected input index is valid.
    // Example:
    // If N = 8, valid sel values are 0 to 7.
    // If sel is 8 or more, it means sel is trying to select
    // an input that does not exist.
    if (sel < N)

        // Select WIDTH number of bits from the combined input bus.
        //
        // Syntax:
        // data_in[starting_bit +: number_of_bits]
        //
        // Here:
        // starting_bit   = sel * WIDTH
        // number_of_bits = WIDTH
        //
        // Example for WIDTH = 8:
        //
        // sel = 0  --> data_in[0  +: 8] = data_in[7:0]
        // sel = 1  --> data_in[8  +: 8] = data_in[15:8]
        // sel = 2  --> data_in[16 +: 8] = data_in[23:16]
        // sel = 3  --> data_in[24 +: 8] = data_in[31:24]
        //
        // Thus, the selected input block is copied to d_out.
        d_out = data_in[sel * WIDTH +: WIDTH];

    else

        // If sel is invalid, assign all zeros to output.
        //
        // {WIDTH{1'b0}} means repeat 1'b0 WIDTH times.
        //
        // Example:
        // WIDTH = 8  --> 8'b00000000
        // WIDTH = 4  --> 4'b0000
        d_out = {WIDTH{1'b0}};

    end

endmodule

n_to_1_mux_tb.v
`timescale 1ns/1ps

module n_to_1_mux_tb;

    // Parameters for this test
    parameter N = 32;
    parameter WIDTH = 8;
    parameter SEL_WIDTH = 5;

    // Combined input bus:
    // 32 inputs × 8 bits = 256 bits
    reg [N*WIDTH-1:0] data_in;

    // Select line
    reg [SEL_WIDTH-1:0] sel;

    // Output
    wire [WIDTH-1:0] d_out;

    // Instantiate generic N:1 MUX
    n_to_1_mux #(
        .N(N),
        .WIDTH(WIDTH),
        .SEL_WIDTH(SEL_WIDTH)
    ) uut (
        .data_in(data_in),
        .sel(sel),
        .d_out(d_out)
    );

    initial begin
        // Generate VCD waveform file
        $dumpfile("n_to_1_mux.vcd");
        $dumpvars(0, n_to_1_mux_tb);

        // Print output in terminal
        $monitor("Time = %0t | sel = %b | d_out = %h",
                 $time, sel, d_out);

        /*
          Assign unique 8-bit values to all 32 inputs.

          data_in[7:0]    = input 0
          data_in[15:8]   = input 1
          data_in[23:16]  = input 2
          ...
          data_in[255:248] = input 31
        */

        data_in[7:0]    = 8'hA1;  // Input 0
        data_in[15:8]   = 8'hB2;  // Input 1
        data_in[23:16]  = 8'hC3;  // Input 2
        data_in[31:24]  = 8'hD4;  // Input 3
        data_in[39:32]  = 8'hE5;  // Input 4
        data_in[47:40]  = 8'hF6;  // Input 5
        data_in[55:48]  = 8'h77;  // Input 6
        data_in[63:56]  = 8'h88;  // Input 7
        data_in[71:64]  = 8'h99;  // Input 8
        data_in[79:72]  = 8'hAA;  // Input 9
        data_in[87:80]  = 8'hBB;  // Input 10
        data_in[95:88]  = 8'hCC;  // Input 11
        data_in[103:96] = 8'hDD;  // Input 12
        data_in[111:104] = 8'hEE; // Input 13
        data_in[119:112] = 8'hFF; // Input 14
        data_in[127:120] = 8'h00; // Input 15
        data_in[135:128] = 8'h11; // Input 16
        data_in[143:136] = 8'h22; // Input 17
        data_in[151:144] = 8'h33; // Input 18
        data_in[159:152] = 8'h44; // Input 19
        data_in[167:160] = 8'h55; // Input 20
        data_in[175:168] = 8'h66; // Input 21
        data_in[183:176] = 8'h77; // Input 22
        data_in[191:184] = 8'h88; // Input 23
        data_in[199:192] = 8'h99; // Input 24
        data_in[207:200] = 8'hAA; // Input 25
        data_in[215:208] = 8'hBB; // Input 26
        data_in[223:216] = 8'hCC; // Input 27
        data_in[231:224] = 8'hDD; // Input 28
        data_in[239:232] = 8'hEE; // Input 29
        data_in[247:240] = 8'hFF; // Input 30
        data_in[255:248] = 8'h00; // Input 31

        // Test every selection value
        sel = 5'b00000; #10;   // Expected output = A1
        sel = 5'b00001; #10;   // Expected output = B2
        sel = 5'b00010; #10;   // Expected output = C3
        sel = 5'b00011; #10;   // Expected output = D4
        sel = 5'b00100; #10;   // Expected output = E5
        sel = 5'b00101; #10;   // Expected output = F6
        sel = 5'b00110; #10;   // Expected output = 77
        sel = 5'b00111; #10;   // Expected output = 88
        sel = 5'b01000; #10;   // Expected output = 99
        sel = 5'b01001; #10;   // Expected output = AA
        sel = 5'b01010; #10;   // Expected output = BB
        sel = 5'b01011; #10;   // Expected output = CC
        sel = 5'b01100; #10;   // Expected output = DD
        sel = 5'b01101; #10;   // Expected output = EE
        sel = 5'b01110; #10;   // Expected output = FF
        sel = 5'b01111; #10;   // Expected output = 00
        sel = 5'b10000; #10;   // Expected output = 11
        sel = 5'b10001; #10;   // Expected output = 22
        sel = 5'b10010; #10;   // Expected output = 33
        sel = 5'b10011; #10;   // Expected output = 44
        sel = 5'b10100; #10;   // Expected output = 55
        sel = 5'b10101; #10;   // Expected output = 66
        sel = 5'b10110; #10;   // Expected output = 77
        sel = 5'b10111; #10;   // Expected output = 88
        sel = 5'b11000; #10;   // Expected output = 99
        sel = 5'b11001; #10;   // Expected output = AA
        sel = 5'b11010; #10;   // Expected output = BB
        sel = 5'b11011; #10;   // Expected output = CC
        sel = 5'b11100; #10;   // Expected output = DD
        sel = 5'b11101; #10;   // Expected output = EE
        sel = 5'b11110; #10;   // Expected output = FF

        $finish;
    end

endmodule

Report_1/n_to_1_mux.vcd
$date
	Tue Jun 23 14:15:28 2026
$end
$version
	Icarus Verilog
$end
$timescale
	1ps
$end
$scope module n_to_1_mux_tb $end
$var wire 8 ! d_out [7:0] $end
$var parameter 32 " N $end
$var parameter 32 # SEL_WIDTH $end
$var parameter 32 $ WIDTH $end
$var reg 256 % data_in [255:0] $end
$var reg 5 & sel [4:0] $end
$scope module uut $end
$var wire 256 ' data_in [255:0] $end
$var wire 5 ( sel [4:0] $end
$var parameter 32 ) N $end
$var parameter 32 * SEL_WIDTH $end
$var parameter 32 + WIDTH $end
$var reg 8 , d_out [7:0] $end
$upscope $end
$upscope $end
$enddefinitions $end
$comment Show the parameter values. $end
$dumpall
b1000 +
b101 *
b100000 )
b1000 $
b101 #
b100000 "
$end
#0
$dumpvars
b10100001 ,
b0 (
b11111111111011101101110111001100101110111010101010011001100010000111011101100110010101010100010000110011001000100001000100000000111111111110111011011101110011001011101110101010100110011000100001110111111101101110010111010100110000111011001010100001 '
b0 &
b11111111111011101101110111001100101110111010101010011001100010000111011101100110010101010100010000110011001000100001000100000000111111111110111011011101110011001011101110101010100110011000100001110111111101101110010111010100110000111011001010100001 %
b10100001 !
$end
#10000
b10110010 !
b10110010 ,
b1 &
b1 (
#20000
b11000011 !
b11000011 ,
b10 &
b10 (
#30000
b11010100 !
b11010100 ,
b11 &
b11 (
#40000
b11100101 !
b11100101 ,
b100 &
b100 (
#50000
b11110110 !
b11110110 ,
b101 &
b101 (
#60000
b1110111 !
b1110111 ,
b110 &
b110 (
#70000
b10001000 !
b10001000 ,
b111 &
b111 (
#80000
b10011001 !
b10011001 ,
b1000 &
b1000 (
#90000
b10101010 !
b10101010 ,
b1001 &
b1001 (
#100000
b10111011 !
b10111011 ,
b1010 &
b1010 (
#110000
b11001100 !
b11001100 ,
b1011 &
b1011 (
#120000
b11011101 !
b11011101 ,
b1100 &
b1100 (
#130000
b11101110 !
b11101110 ,
b1101 &
b1101 (
#140000
b11111111 !
b11111111 ,
b1110 &
b1110 (
#150000
b0 !
b0 ,
b1111 &
b1111 (
#160000
b10001 !
b10001 ,
b10000 &
b10000 (
#170000
b100010 !
b100010 ,
b10001 &
b10001 (
#180000
b110011 !
b110011 ,
b10010 &
b10010 (
#190000
b1000100 !
b1000100 ,
b10011 &
b10011 (
#200000
b1010101 !
b1010101 ,
b10100 &
b10100 (
#210000
b1100110 !
b1100110 ,
b10101 &
b10101 (
#220000
b1110111 !
b1110111 ,
b10110 &
b10110 (
#230000
b10001000 !
b10001000 ,
b10111 &
b10111 (
#240000
b10011001 !
b10011001 ,
b11000 &
b11000 (
#250000
b10101010 !
b10101010 ,
b11001 &
b11001 (
#260000
b10111011 !
b10111011 ,
b11010 &
b11010 (
#270000
b11001100 !
b11001100 ,
b11011 &
b11011 (
#280000
b11011101 !
b11011101 ,
b11100 &
b11100 (
#290000
b11101110 !
b11101110 ,
b11101 &
b11101 (
#300000
b11111111 !
b11111111 ,
b11110 &
b11110 (
